rasterizer/__init__.py
rasterizer/rasterize_kerning.py
rasterizer/rasterizer.py
ndf_rasterizer-0.1.2.dist-info/LICENSE
ndf_rasterizer-0.1.2.dist-info/METADATA
ndf_rasterizer-0.1.2.dist-info/WHEEL
ndf_rasterizer-0.1.2.dist-info/entry_points.txt
ndf_rasterizer-0.1.2.dist-info/top_level.txt
ndf_rasterizer-0.1.2.dist-info/RECORD
